napam/__init__.py
napam/_widget.py
napam/napari.yaml
napam/_tests/__init__.py
napam/_tests/test_widget.py
napam-0.1.3.dist-info/LICENSE
napam-0.1.3.dist-info/METADATA
napam-0.1.3.dist-info/WHEEL
napam-0.1.3.dist-info/entry_points.txt
napam-0.1.3.dist-info/top_level.txt
napam-0.1.3.dist-info/RECORD
