Metadata-Version: 2.1
Name: napam
Version: 0.1.3
Summary: A plugin that allows you to run macros (i.e. python scripts) on the images for any kind of image processing.
Author: Jaison John
Author-email: jjohn@stjude.org
License: BSD-3-Clause
Project-URL: Bug Tracker, https://github.com/JB4Jaison/napam/issues
Project-URL: Source Code, https://github.com/JB4Jaison/napam
Classifier: Development Status :: 3 - Alpha
Classifier: Framework :: napari
Classifier: Intended Audience :: Developers
Classifier: License :: OSI Approved :: BSD License
Classifier: Operating System :: OS Independent
Classifier: Programming Language :: Python
Classifier: Programming Language :: Python :: 3
Classifier: Programming Language :: Python :: 3 :: Only
Classifier: Programming Language :: Python :: 3.8
Classifier: Programming Language :: Python :: 3.9
Classifier: Programming Language :: Python :: 3.10
Classifier: Topic :: Scientific/Engineering :: Image Processing
Requires-Python: >=3.8
License-File: LICENSE
Requires-Dist: numpy
Requires-Dist: magicgui
Requires-Dist: qtpy
Requires-Dist: matplotlib
Requires-Dist: QScintilla
Provides-Extra: testing
Requires-Dist: tox; extra == "testing"
Requires-Dist: pytest; extra == "testing"
Requires-Dist: pytest-cov; extra == "testing"
Requires-Dist: pytest-qt; extra == "testing"
Requires-Dist: napari; extra == "testing"
Requires-Dist: qtpy; extra == "testing"
Requires-Dist: QScintilla; extra == "testing"
